pxr/.libs/libPxrJs.so
pxr_js-25.8.dist-info/METADATA
pxr_js-25.8.dist-info/WHEEL
pxr_js-25.8.dist-info/RECORD
pxr_js-25.8.dist-info/licenses/LICENSE.txt
pxr_js-25.8.dist-info/licenses/NOTICE.txt
